Metadata-Version: 2.1
Name: muggle-speech
Version: 0.1
Summary: 麻瓜语音
Home-page: https://github.com/kerlomz/muggle-speech
Author: kerlomz
License: UNKNOWN
Platform: UNKNOWN
Classifier: Programming Language :: Python :: 3
Classifier: License :: OSI Approved :: MIT License
Classifier: Operating System :: OS Independent
Requires-Python: <3.10
License-File: LICENSE
